c_sqlite3/__init__.py
c_sqlite3/api.py
c_sqlite3-0.0.1.dist-info/METADATA
c_sqlite3-0.0.1.dist-info/WHEEL
c_sqlite3-0.0.1.dist-info/licenses/LICENSE
c_sqlite3-0.0.1.dist-info/RECORD
