Metadata-Version: 2.1
Name: c_sqlite3
Version: 0.0.1
Summary: 一个方便本人操作sqlite的api集
Author-email: 北悸安凉 <2591623190@qq.com>
License: Copyright (c) 2022 The Python Packaging Authority
Classifier: License :: OSI Approved :: MIT License
Classifier: Operating System :: OS Independent
Classifier: Programming Language :: Python :: 3
Requires-Python: >=3.7
